[
    {
        "directory": "/pub/html/ETC"
    },
    {
        "state": "del",
        "id": "UMS/129",
        "type": "본창",
        "depth1": "기타",
        "depth2": "UMS",
        "depth3": "email",
        "depth4": "",
        "name": "129_공통 - EMAIL",
        "worker": "이상미",
        "workdate": null,
        "change": null,
        "complete": "삭제",
        "etc": ["사용안함", "0630: 기획 확인 요청"]
    },
    {
        "state": "del",
        "id": "UMS/141",
        "type": "본창",
        "depth1": "기타",
        "depth2": "UMS",
        "depth3": "email",
        "depth4": "",
        "name": "141_홈페이지-상품추천메일",
        "worker": "이상미",
        "workdate": null,
        "change": null,
        "complete": "삭제",
        "etc": ["사용안함"]
    },
    {
        "state": "del",
        "id": "UMS/168",
        "type": "본창",
        "depth1": "기타",
        "depth2": "UMS",
        "depth3": "email",
        "depth4": "",
        "name": "168_신용정보이용및제공현황",
        "worker": "이상미",
        "workdate": null,
        "change": null,
        "complete": "삭제",
        "etc": ["사용안함", "0630: 기획 확인 요청"]
    },
    {
        "state": null,
        "id": "UMS/170",
        "type": "본창",
        "depth1": "기타",
        "depth2": "UMS",
        "depth3": "email",
        "depth4": "",
        "name": "170_약관 및 상품 설명서",
        "worker": "이상미",
        "workdate": "2023-06-28",
        "change": "2023-07-12",
        "complete": "완료",
        "etc": ["프리뷰 모드로 확인해주세요.", "0712: 이미지 경로 수정"]
    },
    {
        "state": null,
        "id": "UMS/171",
        "type": "본창",
        "depth1": "기타",
        "depth2": "UMS",
        "depth3": "email",
        "depth4": "",
        "name": "171_만기도래안내",
        "worker": "이상미",
        "workdate": "2023-06-28",
        "change": "2023-07-12",
        "complete": "완료",
        "etc": ["프리뷰 모드로 확인해주세요.", "0712: 이미지 경로 수정"]
    },
    {
        "state": null,
        "id": "UMS/172",
        "type": "본창",
        "depth1": "기타",
        "depth2": "UMS",
        "depth3": "email",
        "depth4": "",
        "name": "172_변경거래약정서",
        "worker": "이상미",
        "workdate": "2023-06-28",
        "change": "2023-07-12",
        "complete": "완료",
        "etc": ["프리뷰 모드로 확인해주세요.", "0712: 이미지 경로 수정"]
    },
    {
        "state": null,
        "id": "UMS/173",
        "type": "본창",
        "depth1": "기타",
        "depth2": "UMS",
        "depth3": "email",
        "depth4": "",
        "name": "173_개정사항 안내",
        "worker": "이상미",
        "workdate": "2023-06-28",
        "change": "2023-07-12",
        "complete": "완료",
        "etc": ["프리뷰 모드로 확인해주세요.", "0712: 이미지 경로 수정"]
    },
    {
        "state": null,
        "id": "UMS/174",
        "type": "본창",
        "depth1": "기타",
        "depth2": "UMS",
        "depth3": "email",
        "depth4": "",
        "name": "174_개인정보 이전 안내",
        "worker": "이상미",
        "workdate": "2023-06-28",
        "change": "2023-07-12",
        "complete": "완료",
        "etc": ["프리뷰 모드로 확인해주세요.", "0712: 이미지 경로 수정"]
    },
    {
        "state": null,
        "id": "UMS/175",
        "type": "본창",
        "depth1": "기타",
        "depth2": "UMS",
        "depth3": "email",
        "depth4": "",
        "name": "175_수수료 정책 변경 안내",
        "worker": "이상미",
        "workdate": "2023-06-28",
        "change": "2023-07-12",
        "complete": "완료",
        "etc": ["프리뷰 모드로 확인해주세요.", "0712: 이미지 경로 수정"]
    },
    {
        "state": null,
        "id": "UMS/176",
        "type": "본창",
        "depth1": "기타",
        "depth2": "UMS",
        "depth3": "email",
        "depth4": "",
        "name": "176_적용거래 정책 변경 안내",
        "worker": "이상미",
        "workdate": "2023-06-28",
        "change": "2023-07-12",
        "complete": "완료",
        "etc": ["프리뷰 모드로 확인해주세요.", "0712: 이미지 경로 수정"]
    },
    {
        "state": null,
        "id": "UMS/177",
        "type": "본창",
        "depth1": "기타",
        "depth2": "UMS",
        "depth3": "email",
        "depth4": "",
        "name": "177_마케팅 수신동의 확인메일",
        "worker": "이상미",
        "workdate": "2023-06-28",
        "change": "2023-07-12",
        "complete": "완료",
        "etc": ["프리뷰 모드로 확인해주세요.", "0712: 이미지 경로 수정"]
    },
    {
        "state": null,
        "id": "UMS/178",
        "type": "본창",
        "depth1": "기타",
        "depth2": "UMS",
        "depth3": "email",
        "depth4": "",
        "name": "178_대출약정서_대출상품설명서 전송",
        "worker": "이상미",
        "workdate": "2023-06-28",
        "change": "2023-07-12",
        "complete": "완료",
        "etc": ["프리뷰 모드로 확인해주세요.", "0712: 이미지 경로 수정"]
    },
    {
        "state": "del",
        "id": "UMS/179",
        "type": "본창",
        "depth1": "기타",
        "depth2": "UMS",
        "depth3": "email",
        "depth4": "",
        "name": "179_카드 이용 내역서",
        "worker": "이상미",
        "workdate": "2023-06-28",
        "change": null,
        "complete": "삭제",
        "etc": ["사용안함", "0630: 기획 확인 요청"]
    },
    {
        "state": null,
        "id": "UMS/180",
        "type": "본창",
        "depth1": "기타",
        "depth2": "UMS",
        "depth3": "email",
        "depth4": "",
        "name": "180_공지사항",
        "worker": "이상미",
        "workdate": "2023-06-28",
        "change": "2023-07-12",
        "complete": "완료",
        "etc": ["프리뷰 모드로 확인해주세요.", "0712: 이미지 경로 수정"]
    },
    {
        "state": null,
        "id": "UMS/181",
        "type": "본창",
        "depth1": "기타",
        "depth2": "UMS",
        "depth3": "email",
        "depth4": "",
        "name": "181_예적금 만기안내",
        "worker": "이상미",
        "workdate": "2023-06-28",
        "change": "2023-07-12",
        "complete": "완료",
        "etc": ["프리뷰 모드로 확인해주세요.", "0712: 이미지 경로 수정"]
    },
    {
        "state": null,
        "id": "UMS/182",
        "type": "본창",
        "depth1": "기타",
        "depth2": "UMS",
        "depth3": "email",
        "depth4": "",
        "name": "182_대출 만기안내",
        "worker": "이상미",
        "workdate": "2023-06-28",
        "change": "2023-07-12",
        "complete": "완료",
        "etc": ["0705:문구추가", "0630:문구수정", "프리뷰 모드로 확인해주세요.", "0712: 이미지 경로 수정"]
    },
    {
        "state": null,
        "id": "UMS/183",
        "type": "본창",
        "depth1": "기타",
        "depth2": "UMS",
        "depth3": "email",
        "depth4": "",
        "name": "183_증명서 발송",
        "worker": "이상미",
        "workdate": "2023-06-28",
        "change": "2023-07-12",
        "complete": "완료",
        "etc": ["프리뷰 모드로 확인해주세요.", "0712: 이미지 경로 수정"]
    },
    {
        "state": null,
        "id": "UMS/184",
        "type": "본창",
        "depth1": "기타",
        "depth2": "UMS",
        "depth3": "email",
        "depth4": "",
        "name": "184_수기",
        "worker": "이상미",
        "workdate": "2023-06-28",
        "change": "2023-07-12",
        "complete": "완료",
        "etc": ["프리뷰 모드로 확인해주세요.", "0712: 이미지 경로 수정"]
    },
    {
        "state": "del",
        "id": "UMS/190",
        "type": "본창",
        "depth1": "기타",
        "depth2": "UMS",
        "depth3": "email",
        "depth4": "",
        "name": "190_사이다_PPR 서비스 발송",
        "worker": "이상미",
        "workdate": "2023-06-28",
        "change": null,
        "complete": "삭제",
        "etc": ["170, 178과 통합", "프리뷰 모드로 확인해주세요."]
    },
    {
        "state": null,
        "id": "UMS/191",
        "type": "본창",
        "depth1": "기타",
        "depth2": "UMS",
        "depth3": "email",
        "depth4": "",
        "name": "191_오픈뱅킹 서비스",
        "worker": "이상미",
        "workdate": "2023-06-28",
        "change": "2023-09-01",
        "complete": "완료",
        "etc": ["0901: 문구변뎡","프리뷰 모드로 확인해주세요.", "0712: 이미지 경로 수정"]
    },
    {
        "state": null,
        "id": "UMS/306",
        "type": "본창",
        "depth1": "기타",
        "depth2": "UMS",
        "depth3": "email",
        "depth4": "",
        "name": "306_사이다_엑셀첨부_이메일",
        "worker": "이상미",
        "workdate": "2023-06-28",
        "change": "2023-07-12",
        "complete": "완료",
        "etc": ["프리뷰 모드로 확인해주세요.", "0712: 이미지 경로 수정"]
    },
    {
        "state": "del",
        "id": "UMS/307",
        "type": "본창",
        "depth1": "기타",
        "depth2": "UMS",
        "depth3": "email",
        "depth4": "",
        "name": "307_비대면고도화_제증명서_이메일_발송",
        "worker": "이상미",
        "workdate": "2023-06-28",
        "change": null,
        "complete": "삭제",
        "etc": ["183과 통합", "프리뷰 모드로 확인해주세요."]
    },
    {
        "state": "del",
        "id": "UMS/308",
        "type": "본창",
        "depth1": "기타",
        "depth2": "UMS",
        "depth3": "email",
        "depth4": "",
        "name": "308_비대면고도화_상품및약관_이메일_발송",
        "worker": "이상미",
        "workdate": "2023-06-28",
        "change": null,
        "complete": "삭제",
        "etc": ["170, 178과 통합", "프리뷰 모드로 확인해주세요."]
    },
    {
        "state": null,
        "id": "UMS/new_001",
        "type": "본창",
        "depth1": "기타",
        "depth2": "UMS",
        "depth3": "email",
        "depth4": "",
        "name": "신규_커플통장 금융거래 제공사실 안내",
        "worker": "이상미",
        "workdate": "2023-06-28",
        "change": "2023-07-12",
        "complete": "완료",
        "etc": ["0630:문구수정", "프리뷰 모드로 확인해주세요.", "0712: 이미지 경로 수정"]
    
    },
    {
        "state": null,
        "id": "NICE/CRD_0101",
        "type": "본창",
        "depth1": "기타",
        "depth2": "NICE",
        "depth3": "내 신용정보 요약",
        "depth4": "",
        "name": "",
        "worker": "김용호",
        "workdate": "2023-07-07",
        "change": null,
        "complete": "완료",
        "etc": null
    },
    {
        "state": null,
        "id": "NICE/CRD_0201",
        "type": "본창",
        "depth1": "기타",
        "depth2": "NICE",
        "depth3": "신용평점",
        "depth4": "",
        "name": "",
        "worker": "김용호",
        "workdate": "2023-07-07",
        "change": null,
        "complete": "완료",
        "etc": null
    },
    {
        "state": null,
        "id": "NICE/CRD_0202_01",
        "type": "본창",
        "depth1": "기타",
        "depth2": "NICE",
        "depth3": "소득정보",
        "depth4": "",
        "name": "",
        "worker": "김용호",
        "workdate": "2023-07-07",
        "change": null,
        "complete": "완료",
        "etc": null
    },
    {
        "state": null,
        "id": "NICE/CRD_0202_02",
        "type": "본창",
        "depth1": "기타",
        "depth2": "NICE",
        "depth3": "소득정보",
        "depth4": "없음",
        "name": "",
        "worker": "김용호",
        "workdate": "2023-07-07",
        "change": null,
        "complete": "완료",
        "etc": null
    },
    {
        "state": null,
        "id": "NICE/CRD_0203_01",
        "type": "본창",
        "depth1": "기타",
        "depth2": "NICE",
        "depth3": "조회내역",
        "depth4": "",
        "name": "",
        "worker": "김용호",
        "workdate": "2023-07-07",
        "change": null,
        "complete": "완료",
        "etc": null
    },
    {
        "state": null,
        "id": "NICE/CRD_0203_02",
        "type": "본창",
        "depth1": "기타",
        "depth2": "NICE",
        "depth3": "조회내역",
        "depth4": "없음",
        "name": "",
        "worker": "김용호",
        "workdate": "2023-07-07",
        "change": null,
        "complete": "완료",
        "etc": null
    },
    {
        "state": null,
        "id": "NICE/CRD_0204_01",
        "type": "본창",
        "depth1": "기타",
        "depth2": "NICE",
        "depth3": "변동내역",
        "depth4": "",
        "name": "",
        "worker": "김용호",
        "workdate": "2023-07-07",
        "change": null,
        "complete": "완료",
        "etc": null
    },
    {
        "state": null,
        "id": "NICE/CRD_0204_02",
        "type": "본창",
        "depth1": "기타",
        "depth2": "NICE",
        "depth3": "변동내역",
        "depth4": "없음",
        "name": "",
        "worker": "김용호",
        "workdate": "2023-07-07",
        "change": null,
        "complete": "완료",
        "etc": null
    },
    {
        "state": null,
        "id": "NICE/CRD_0301_01",
        "type": "본창",
        "depth1": "기타",
        "depth2": "NICE",
        "depth3": "카드",
        "depth4": "",
        "name": "",
        "worker": "김용호",
        "workdate": "2023-07-07",
        "change": null,
        "complete": "완료",
        "etc": null
    },
    {
        "state": null,
        "id": "NICE/CRD_0301_02",
        "type": "본창",
        "depth1": "기타",
        "depth2": "NICE",
        "depth3": "카드",
        "depth4": "없음",
        "name": "",
        "worker": "김용호",
        "workdate": "2023-07-07",
        "change": null,
        "complete": "완료",
        "etc": null
    },
    {
        "state": null,
        "id": "NICE/CRD_0302_01",
        "type": "본창",
        "depth1": "기타",
        "depth2": "NICE",
        "depth3": "대출",
        "depth4": "",
        "name": "",
        "worker": "김용호",
        "workdate": "2023-07-07",
        "change": null,
        "complete": "완료",
        "etc": null
    },
    {
        "state": null,
        "id": "NICE/CRD_0302_02",
        "type": "본창",
        "depth1": "기타",
        "depth2": "NICE",
        "depth3": "대출",
        "depth4": "없음",
        "name": "",
        "worker": "김용호",
        "workdate": "2023-07-07",
        "change": null,
        "complete": "완료",
        "etc": null
    },
    {
        "state": null,
        "id": "NICE/CRD_0303_01",
        "type": "본창",
        "depth1": "기타",
        "depth2": "NICE",
        "depth3": "연체",
        "depth4": "",
        "name": "",
        "worker": "김용호",
        "workdate": "2023-07-07",
        "change": null,
        "complete": "완료",
        "etc": null
    },
    {
        "state": null,
        "id": "NICE/CRD_0303_02",
        "type": "본창",
        "depth1": "기타",
        "depth2": "NICE",
        "depth3": "연체",
        "depth4": "없음",
        "name": "",
        "worker": "김용호",
        "workdate": "2023-07-07",
        "change": null,
        "complete": "완료",
        "etc": null
    },
    {
        "state": null,
        "id": "NICE/CRD_0304_01",
        "type": "본창",
        "depth1": "기타",
        "depth2": "NICE",
        "depth3": "보증",
        "depth4": "",
        "name": "",
        "worker": "김용호",
        "workdate": "2023-07-07",
        "change": null,
        "complete": "완료",
        "etc": null
    },
    {
        "state": null,
        "id": "NICE/CRD_0304_02",
        "type": "본창",
        "depth1": "기타",
        "depth2": "NICE",
        "depth3": "보증",
        "depth4": "없음",
        "name": "",
        "worker": "김용호",
        "workdate": "2023-07-07",
        "change": null,
        "complete": "완료",
        "etc": null
    },
    {
        "state": null,
        "id": "NICE/CRD_loding",
        "type": "본창",
        "depth1": "기타",
        "depth2": "NICE",
        "depth3": "로딩",
        "depth4": "",
        "name": "",
        "worker": "김용호",
        "workdate": "2023-07-07",
        "change": null,
        "complete": "완료",
        "etc": null
    },
    {
        "state": null,
        "id": "NICE/ERROR_pop",
        "type": "본창",
        "depth1": "기타",
        "depth2": "NICE",
        "depth3": "팝업",
        "depth4": "오류",
        "name": "",
        "worker": "김용호",
        "workdate": "2023-07-07",
        "change": null,
        "complete": "완료",
        "etc": null
    },
    {
        "state": null,
        "id": "NICE/LOGOUT_pop",
        "type": "본창",
        "depth1": "기타",
        "depth2": "NICE",
        "depth3": "팝업",
        "depth4": "로그아웃",
        "name": "",
        "worker": "김용호",
        "workdate": "2023-07-07",
        "change": null,
        "complete": "완료",
        "etc": null
    },
    {
        "state": null,
        "id": "NICE/LODING_pop",
        "type": "본창",
        "depth1": "기타",
        "depth2": "NICE",
        "depth3": "팝업",
        "depth4": "로딩 후 실패",
        "name": "",
        "worker": "김용호",
        "workdate": "2023-07-07",
        "change": null,
        "complete": "완료",
        "etc": null
    },
    {
        "state": null,
        "id": "MIG/index01",
        "type": "본창",
        "depth1": "기타",
        "depth2": "MIG",
        "depth3": "",
        "depth4": "",
        "name": "마이그레이션 시점",
        "worker": "김용호",
        "workdate": "2023-08-11",
        "change": null,
        "complete": "완료",
        "etc": null
    },
    {
        "state": null,
        "id": "MIG/index02",
        "type": "본창",
        "depth1": "기타",
        "depth2": "MIG",
        "depth3": "",
        "depth4": "",
        "name": "이행시점",
        "worker": "김용호",
        "workdate": "2023-08-11",
        "change": null,
        "complete": "완료",
        "etc": null
    },
    {
        "state": null,
        "id": "MIG/index03",
        "type": "본창",
        "depth1": "기타",
        "depth2": "MIG",
        "depth3": "",
        "depth4": "",
        "name": "앱 배포 완료",
        "worker": "김용호",
        "workdate": "2023-08-11",
        "change": null,
        "complete": "완료",
        "etc": null
    },
    {
        "state": null,
        "id": "MIG/index04",
        "type": "본창",
        "depth1": "기타",
        "depth2": "MIG",
        "depth3": "",
        "depth4": "",
        "name": "앱 배포 완료(as-is실행시)",
        "worker": "김용호",
        "workdate": "2023-08-11",
        "change": null,
        "complete": "완료",
        "etc": null
    },
    {
        "state": null,
        "id": "PDF/MSB_PDF_01",
        "type": "본창",
        "depth1": "기타",
        "depth2": "PDF",
        "depth3": "",
        "depth4": "",
        "name": "PDF 인쇄",
        "worker": "백은숙",
        "workdate": "2023-11-07",
        "change": null,
        "complete": "완료",
        "etc": ["1107: 기획추가","개발에 별도파일 전달"]
    },
    {
        "state": null,
        "id": "STA/PRIVACY_standalone",
        "type": "본창",
        "depth1": "기타",
        "depth2": "약관",
        "depth3": "",
        "depth4": "",
        "name": "개인정보처리방침(단일파일)",
        "worker": "윤영규",
        "workdate": "2023-11-14",
        "change": null,
        "complete": "완료",
        "etc": ["1114:심사용 제출 단일파일 형식 개인정보처리방침"]
    }
]